fdock_cli/__init__.py
fdock_cli/__main__.py
fdock_cli/cli.py
fdock_cli/install.py
fdock_cli/scripts/hello.sh
fdock_cli/scripts/root.sh
fdock_cli/scripts/hello.sh
fdock_cli/scripts/root.sh
fdock_cli-2.5.6.dist-info/METADATA
fdock_cli-2.5.6.dist-info/WHEEL
fdock_cli-2.5.6.dist-info/entry_points.txt
fdock_cli-2.5.6.dist-info/licenses/LICENSE
fdock_cli-2.5.6.dist-info/RECORD
