Metadata-Version: 2.4
Name: fdock_cli
Version: 2.5.6
Summary: Un outil CLI puissant pour initialiser et gérer vos projets Python avec style !
Project-URL: Homepage, https://github.com/NathanQuantum/fdock
Project-URL: Documentation, https://github.com/NathanQuantum/fdock#readme
Author-email: fdock <fdock@example.com>
License-Expression: MIT
License-File: LICENSE
Keywords: cli,development,initialization,project,python,tools
Classifier: Development Status :: 4 - Beta
Classifier: Intended Audience :: Developers
Classifier: License :: OSI Approved :: MIT License
Classifier: Operating System :: OS Independent
Classifier: Programming Language :: Python :: 3
Classifier: Programming Language :: Python :: 3.10
Classifier: Programming Language :: Python :: 3.11
Classifier: Programming Language :: Python :: 3.12
Classifier: Topic :: Software Development :: Build Tools
Classifier: Topic :: System :: Systems Administration
Classifier: Topic :: Utilities
Requires-Python: >=3.10
